aram/__init__.py
aram/aram.py
aram/cmb.py
aram/objects.py
aram/tools.py
aram/resources/cmb_spectra/act+wmap.npy
aram/resources/cmb_spectra/act.dat
aram/resources/cmb_spectra/wmap.dat
aram/resources/sites/site_dict
aram/resources/weather/avg
aram/resources/weather/gen
aram/resources/weather/hgt
aram/resources/weather/max
aram/resources/weather/min
aram/resources/weather/rms
aram-0.1.2.dist-info/LICENSE
aram-0.1.2.dist-info/METADATA
aram-0.1.2.dist-info/WHEEL
aram-0.1.2.dist-info/top_level.txt
aram-0.1.2.dist-info/RECORD
