Metadata-Version: 2.1
Name: aram
Version: 0.1.2
Summary: Auto-Regressive Atmospheric Modeling
Home-page: https://github.com/tomachito/aram
Author: Thomas Morris
License: UNKNOWN
Platform: UNKNOWN
Classifier: Programming Language :: Python :: 3
Classifier: License :: OSI Approved :: MIT License
Classifier: Operating System :: OS Independent
Requires-Python: >=3.7
Requires-Dist: numpy
Requires-Dist: scipy
Requires-Dist: ephem
